imagesc/__init__.py
imagesc/examples.py
imagesc/imagesc.py
imagesc/utils/__init__.py
imagesc/utils/adjmat_vec.py
imagesc/utils/savefig.py
imagesc-0.3.0.dist-info/LICENSE
imagesc-0.3.0.dist-info/METADATA
imagesc-0.3.0.dist-info/WHEEL
imagesc-0.3.0.dist-info/top_level.txt
imagesc-0.3.0.dist-info/RECORD
