Metadata-Version: 2.1
Name: imagesc
Version: 0.3.0
Summary: imagesc is an Python package to create heatmaps in a easy way.
Home-page: https://github.com/erdogant/imagesc
Download-URL: https://github.com/erdogant/imagesc/archive/0.3.0.tar.gz
Author: Erdogan Taskesen
Author-email: erdogant@gmail.com
Classifier: Programming Language :: Python :: 3
Classifier: License :: OSI Approved :: MIT License
Classifier: Operating System :: OS Independent
Requires-Python: >=3
License-File: LICENSE
Requires-Dist: matplotlib
Requires-Dist: numpy
Requires-Dist: pandas
Requires-Dist: ismember
Requires-Dist: packaging
Requires-Dist: d3heatmap
